CHANGES.txt
CONTRIBUTORS.txt
MANIFEST.in
README.txt
bootstrap.py
buildout.cfg
setup.cfg
setup.py
docs/LICENSE.txt
docs/agpl-3.0.txt
src/wasgehtengine/__init__.py
src/wasgehtengine.contenttypes.egg-info/PKG-INFO
src/wasgehtengine.contenttypes.egg-info/SOURCES.txt
src/wasgehtengine.contenttypes.egg-info/dependency_links.txt
src/wasgehtengine.contenttypes.egg-info/entry_points.txt
src/wasgehtengine.contenttypes.egg-info/namespace_packages.txt
src/wasgehtengine.contenttypes.egg-info/not-zip-safe
src/wasgehtengine.contenttypes.egg-info/requires.txt
src/wasgehtengine.contenttypes.egg-info/top_level.txt
src/wasgehtengine/contenttypes/__init__.py
src/wasgehtengine/contenttypes/behaviors.py
src/wasgehtengine/contenttypes/blogfolder.py
src/wasgehtengine/contenttypes/blogitem.py
src/wasgehtengine/contenttypes/configure.zcml
src/wasgehtengine/contenttypes/event.py
src/wasgehtengine/contenttypes/eventfolder.py
src/wasgehtengine/contenttypes/eventimportstatus.py
src/wasgehtengine/contenttypes/eventimportstatusfolder.py
src/wasgehtengine/contenttypes/eventlist.py
src/wasgehtengine/contenttypes/movie.py
src/wasgehtengine/contenttypes/osmimportstatus.py
src/wasgehtengine/contenttypes/osmimportstatusfolder.py
src/wasgehtengine/contenttypes/permissions.zcml
src/wasgehtengine/contenttypes/screening.py
src/wasgehtengine/contenttypes/screeningfolder.py
src/wasgehtengine/contenttypes/siteroot.py
src/wasgehtengine/contenttypes/testing.py
src/wasgehtengine/contenttypes/venue.py
src/wasgehtengine/contenttypes/venuefolder.py
src/wasgehtengine/contenttypes/venuelist.py
src/wasgehtengine/contenttypes/blogfolder_templates/view.pt
src/wasgehtengine/contenttypes/blogitem_templates/blogitemview.pt
src/wasgehtengine/contenttypes/event_templates/view.pt
src/wasgehtengine/contenttypes/eventfolder_templates/eventfolder_viewlet.pt
src/wasgehtengine/contenttypes/eventfolder_templates/view.pt
src/wasgehtengine/contenttypes/eventimportstatus_templates/view.pt
src/wasgehtengine/contenttypes/eventimportstatusfolder_templates/eventimportstatusfolder_viewlet.pt
src/wasgehtengine/contenttypes/eventimportstatusfolder_templates/view.pt
src/wasgehtengine/contenttypes/eventlist_templates/dayview.pt
src/wasgehtengine/contenttypes/movie_templates/view.pt
src/wasgehtengine/contenttypes/osmimportstatus_templates/view.pt
src/wasgehtengine/contenttypes/osmimportstatusfolder_templates/osmimportstatusfolder_viewlet.pt
